toxinpred2/Database/data.phr
toxinpred2/Database/data.pin
toxinpred2/Database/data.psq
toxinpred2/Database/pos_motif.txt
toxinpred2/blast_binaries/linux/blastp
toxinpred2/blast_binaries/mac/blastp
toxinpred2/blast_binaries/windows/blastp.exe
toxinpred2/blast_binaries/windows/nghttp2.dll
toxinpred2/model/RF_model.onnx.zip
toxinpred2/progs/MERCI_motif_locator.pl
toxinpred2/python_scripts/__init__.py
toxinpred2/python_scripts/toxinpred2.py
toxinpred2-1.1.dist-info/LICENSE
toxinpred2-1.1.dist-info/METADATA
toxinpred2-1.1.dist-info/WHEEL
toxinpred2-1.1.dist-info/entry_points.txt
toxinpred2-1.1.dist-info/top_level.txt
toxinpred2-1.1.dist-info/RECORD
