Metadata-Version: 2.1
Name: toxinpred2
Version: 1.1
Summary: A tool to predict toxic and non-toxic proteins
Home-page: https://github.com/raghavagps/toxinpred2
License: UNKNOWN
Platform: UNKNOWN
Requires-Python: >=3.6
Requires-Dist: numpy
Requires-Dist: pandas
Requires-Dist: argparse
Requires-Dist: joblib
Requires-Dist: onnxruntime
